actionsheets/__init__.py
actionsheets/__main__.py
actionsheets/console.py
actionsheets/data/R/basic/basic.toml
actionsheets/data/R/basic/factor.toml
actionsheets/data/R/basic/formula.toml
actionsheets/data/R/basic/matrix.toml
actionsheets/data/R/basic/vector.toml
actionsheets/data/R/data.table.toml
actionsheets/data/R/devtools/devtools.toml
actionsheets/data/R/devtools/roxygen2.toml
actionsheets/data/R/eval.toml
actionsheets/data/R/parallel.toml
actionsheets/data/R/plot/ggplot2.toml
actionsheets/data/R/plot/plot.toml
actionsheets/data/R/r.toml
actionsheets/data/R/rmarkdown.toml
actionsheets/data/R/stats/formula.toml
actionsheets/data/R/stats/nlme.toml
actionsheets/data/R/stats/rstan.toml
actionsheets/data/R/stats/stats.toml
actionsheets/data/__init__.py
actionsheets/data/python/cli.toml
actionsheets/data/python/collections/collections.toml
actionsheets/data/python/collections/dict.toml
actionsheets/data/python/collections/iter.toml
actionsheets/data/python/collections/list.toml
actionsheets/data/python/collections/set.toml
actionsheets/data/python/collections/tuple.toml
actionsheets/data/python/devtools/devtools.toml
actionsheets/data/python/devtools/pip.toml
actionsheets/data/python/devtools/poetry.toml
actionsheets/data/python/devtools/pytest.toml
actionsheets/data/python/filesystem/filesystem.toml
actionsheets/data/python/filesystem/path.toml
actionsheets/data/python/numpy/matrix.toml
actionsheets/data/python/numpy/ndarray.toml
actionsheets/data/python/numpy/numpy.toml
actionsheets/data/python/numpy/scalar.toml
actionsheets/data/python/numpy/vector.toml
actionsheets/data/python/pandas/pandas.dataframe.toml
actionsheets/data/python/pandas/pandas.toml
actionsheets/data/python/pkg.toml
actionsheets/data/python/plot/plot.toml
actionsheets/data/python/plot/seaborn.toml
actionsheets/data/python/polars/polars.dataframe.toml
actionsheets/data/python/polars/polars.toml
actionsheets/data/python/python.toml
actionsheets/data/python/scalars/date.toml
actionsheets-0.2.0.dist-info/LICENSE
actionsheets-0.2.0.dist-info/METADATA
actionsheets-0.2.0.dist-info/WHEEL
actionsheets-0.2.0.dist-info/RECORD
