Metadata-Version: 2.1
Name: actionsheets
Version: 0.2.0
Summary: Provides a large collection of searchable quick-reference code-snippet sheets defined in terms of a desired action and corresponding code snippet.
Home-page: https://actionsheets.streamlit.app/
License: MIT
Keywords: cheatsheets,code snippets,quick reference
Author: Niek Den Teuling
Requires-Python: >=3.11,<4.0
Classifier: Development Status :: 4 - Beta
Classifier: Intended Audience :: Developers
Classifier: Intended Audience :: End Users/Desktop
Classifier: License :: OSI Approved :: MIT License
Classifier: Natural Language :: English
Classifier: Operating System :: OS Independent
Classifier: Programming Language :: Python :: 3
Classifier: Programming Language :: Python :: 3.11
Classifier: Programming Language :: Python :: 3.12
Classifier: Programming Language :: R
Classifier: Topic :: Documentation
Classifier: Topic :: Software Development :: Documentation
Requires-Dist: polars (>=1.0,<2.0)
Requires-Dist: rich (>=13.7,<14.0)
Project-URL: Issue tracker, https://github.com/niekdt/actionsheets/issues
Project-URL: Repository, https://github.com/niekdt/actionsheets
